{
  "_fv": 24,
  "_type": "achievement",
  "definition": {
    "achievementName": "Undiscovered",
    "achievementDescription": "Milk the Cloud Potman with Levitated or Wind Helmet on.",
    "achievementIcon": {
      "value": "CUSTOM:Yunnaitong"
    },
    "background": "Default",
    "disableDisplay": false,
    "showPopup": true,
    "announceToChat": true,
    "hideIfNotCompleted": false,
    "rewardLoot": [],
    "rewardRecipes": [],
    "rewardFunction": "No function",
    "rewardXP": 0,
    "achievementType": "task",
    "parent": {
      "value": "CUSTOM:GongJiBingQuNai"
    },
    "triggerxml": "<xml xmlns=\"https://developers.google.com/blockly/xml\"><block type=\"custom_trigger\" x=\"39\" y=\"43\"><next><block type=\"advancement_trigger\" deletable=\"false\"></block></next></block></xml>"
  }
}